odoo9_addon_mrp_bom_structure_xlsx_level_1-9.0.1.0.0-py2.7-nspkg.pth
odoo9_addon_mrp_bom_structure_xlsx_level_1-9.0.1.0.0.dist-info/top_level.txt
odoo9_addon_mrp_bom_structure_xlsx_level_1-9.0.1.0.0.dist-info/WHEEL
odoo9_addon_mrp_bom_structure_xlsx_level_1-9.0.1.0.0.dist-info/RECORD
odoo9_addon_mrp_bom_structure_xlsx_level_1-9.0.1.0.0.dist-info/metadata.json
odoo9_addon_mrp_bom_structure_xlsx_level_1-9.0.1.0.0.dist-info/DESCRIPTION.rst
odoo9_addon_mrp_bom_structure_xlsx_level_1-9.0.1.0.0.dist-info/METADATA
odoo9_addon_mrp_bom_structure_xlsx_level_1-9.0.1.0.0.dist-info/namespace_packages.txt
odoo_addons/mrp_bom_structure_xlsx_level_1/__openerp__.py
odoo_addons/mrp_bom_structure_xlsx_level_1/__init__.py
odoo_addons/mrp_bom_structure_xlsx_level_1/README.rst
odoo_addons/mrp_bom_structure_xlsx_level_1/report/bom_structure_xlsx.py
odoo_addons/mrp_bom_structure_xlsx_level_1/report/__init__.py
odoo_addons/mrp_bom_structure_xlsx_level_1/report/bom_structure_xlsx.xml
odoo_addons/mrp_bom_structure_xlsx_level_1/static/description/index.html
odoo_addons/mrp_bom_structure_xlsx_level_1/static/description/icon.png
